gaiaunlimited/__init__.py
gaiaunlimited/fetch_utils.py
gaiaunlimited/scanninglaw.py
gaiaunlimited/utils.py
gaiaunlimited/data/apogee_sampling_fractions.csv
gaiaunlimited/data/horizons_results_gaia.txt
gaiaunlimited/data/dr2/Astrometry.csv
gaiaunlimited/data/dr2/Photometry.csv
gaiaunlimited/data/dr2/Spectroscopy.csv
gaiaunlimited/data/dr3/Astrometry.csv
gaiaunlimited/data/dr3/Photometry.csv
gaiaunlimited/data/dr3/Spectroscopy.csv
gaiaunlimited/selectionfunctions/__init__.py
gaiaunlimited/selectionfunctions/apogee.py
gaiaunlimited/selectionfunctions/binaries.py
gaiaunlimited/selectionfunctions/subsample.py
gaiaunlimited/selectionfunctions/survey.py
gaiaunlimited/selectionfunctions/surveyTCG.py
gaiaunlimited-0.3.0.dist-info/LICENSE
gaiaunlimited-0.3.0.dist-info/METADATA
gaiaunlimited-0.3.0.dist-info/WHEEL
gaiaunlimited-0.3.0.dist-info/top_level.txt
gaiaunlimited-0.3.0.dist-info/RECORD
