Metadata-Version: 2.1
Name: gaiaunlimited
Version: 0.3.0
Summary: Tools for manipulating Gaia selection functions.
Home-page: https://github.com/GaiaUnlimited/gaiaunlimited
Author: GaiaUnlimited
Maintainer: Alfred Castro-Ginard, Tristan Cantat-Gaudin
Maintainer-email: acastro@strw.leidenuniv.nl, cantat@mpia-hd.mpg.de
Project-URL: Bug Tracker, https://github.com/GaiaUnlimited/gaiaunlimited/issues
Keywords: astronomy,Gaia,selection function,scanning law
Classifier: Programming Language :: Python :: 3
Classifier: License :: OSI Approved :: MIT License
Classifier: Operating System :: OS Independent
Classifier: Intended Audience :: Science/Research
Classifier: Topic :: Scientific/Engineering :: Astronomy
Requires-Python: >=3.7
License-File: LICENSE
Requires-Dist: numpy
Requires-Dist: scipy >=1.6.0
Requires-Dist: astropy
Requires-Dist: astropy-healpix
Requires-Dist: astroquery
Requires-Dist: pandas
Requires-Dist: xarray
Requires-Dist: healpy
Requires-Dist: h5py
Requires-Dist: tqdm
Requires-Dist: requests
Requires-Dist: astromet
